regelum/__init__.py
regelum/node/__init__.py
regelum/node/base.py
regelum/node/classic_control/__init__.py
regelum/node/classic_control/controllers/__init__.py
regelum/node/classic_control/controllers/backstepping.py
regelum/node/classic_control/controllers/energy_based.py
regelum/node/classic_control/controllers/lqr.py
regelum/node/classic_control/controllers/mpc.py
regelum/node/classic_control/controllers/pid.py
regelum/node/classic_control/controllers/scipy_mpc.py
regelum/node/classic_control/envs/__init__.py
regelum/node/classic_control/envs/continuous/__init__.py
regelum/node/classic_control/envs/continuous/cartpole.py
regelum/node/classic_control/envs/continuous/dc_motor.py
regelum/node/classic_control/envs/continuous/double_pendulum.py
regelum/node/classic_control/envs/continuous/kin_point.py
regelum/node/classic_control/envs/continuous/mass_spring_damper.py
regelum/node/classic_control/envs/continuous/pendulum.py
regelum/node/classic_control/envs/continuous/pendulum_friction.py
regelum/node/classic_control/envs/continuous/pendulum_motor.py
regelum/node/classic_control/envs/continuous/three_wheeled_robot.py
regelum/node/classic_control/envs/continuous/three_wheeled_robot_dyn.py
regelum/node/classic_control/envs/discrete/__init__.py
regelum/node/classic_control/envs/discrete/chain.py
regelum/node/classic_control/envs/discrete/discrete_pendulum.py
regelum/node/classic_control/envs/discrete/grid_world.py
regelum/node/classic_control/observers/__init__.py
regelum/node/classic_control/observers/unscented_kalman_filter.py
regelum/node/core/__init__.py
regelum/node/core/globals.py
regelum/node/core/inputs.py
regelum/node/core/types.py
regelum/node/core/variable.py
regelum/node/graph.py
regelum/node/interfaces/__init__.py
regelum/node/interfaces/base.py
regelum/node/interfaces/graph.py
regelum/node/interfaces/modifiers.py
regelum/node/interfaces/node.py
regelum/node/logging.py
regelum/node/memory/__init__.py
regelum/node/memory/buffer.py
regelum/node/memory/lag.py
regelum-0.1.0.dist-info/LICENSE
regelum-0.1.0.dist-info/METADATA
regelum-0.1.0.dist-info/WHEEL
regelum-0.1.0.dist-info/RECORD
