Metadata-Version: 2.3
Name: regelum
Version: 0.1.0
Summary: Regelum is a flexibly configurable framework for computational graph construction and execution.
License: MIT
Author: Georgiy Malaniya
Author-email: pwlsd.gm@gmail.com
Requires-Python: >=3.12
Classifier: License :: OSI Approved :: MIT License
Classifier: Programming Language :: Python :: 3
Classifier: Programming Language :: Python :: 3.12
Classifier: Programming Language :: Python :: 3.13
Provides-Extra: dev
Requires-Dist: black (>=24.3.0) ; extra == "dev"
Requires-Dist: casadi (>=3.6.7)
Requires-Dist: dask[complete] (>=2024.12.1)
Requires-Dist: graphviz (>=0.20.3)
Requires-Dist: loguru (>=0.7.3)
Requires-Dist: matplotlib (>=3.9.2)
Requires-Dist: mkdocs-autorefs (>=1.2.0) ; extra == "dev"
Requires-Dist: mkdocs-gen-files (>=0.5.0) ; extra == "dev"
Requires-Dist: mkdocs-jupyter (>=0.25.1) ; extra == "dev"
Requires-Dist: mkdocs-literate-nav (>=0.6.1) ; extra == "dev"
Requires-Dist: mkdocs-macros-plugin (>=1.0.5) ; extra == "dev"
Requires-Dist: mkdocs-material (>=9.5.47) ; extra == "dev"
Requires-Dist: mkdocs-section-index (>=0.3.8) ; extra == "dev"
Requires-Dist: mypy (>=1.8.0) ; extra == "dev"
Requires-Dist: omegaconf (>=2.3.0)
Requires-Dist: opencv-python (>=4.11.0.86)
Requires-Dist: pandas (>=2.2.3)
Requires-Dist: pre-commit (>=3.6.0) ; extra == "dev"
Requires-Dist: pygame (>=2.6.1)
Requires-Dist: pylint (>=3.0.3) ; extra == "dev"
Requires-Dist: pytest (>=8.3.4) ; extra == "dev"
Requires-Dist: pytest-cov (>=4.1.0) ; extra == "dev"
Requires-Dist: ruff (>=0.3.0) ; extra == "dev"
Requires-Dist: scipy (>=1.14.1)
Requires-Dist: torch (>=2.4.1)
Requires-Dist: types-PyYAML (>=6.0.12) ; extra == "dev"
Requires-Dist: types-requests (>=2.32.0.20241016) ; extra == "dev"
Requires-Dist: types-setuptools (>=75.6.0.20241223) ; extra == "dev"
